hc_passphrase-1.2.1.dist-info/METADATA
hc_passphrase-1.2.1.dist-info/RECORD
hc_passphrase-1.2.1.dist-info/WHEEL
hc_passphrase-1.2.1.dist-info/entry_points.txt
hc_passphrase-1.2.1.dist-info/top_level.txt
passphrase/__init__.py
passphrase/__main__.py
passphrase/aux.py
passphrase/calc.py
passphrase/passphrase.py
passphrase/random.py
passphrase/secrets.py
passphrase/settings.py
passphrase/wordlist.py
