Metadata-Version: 2.1
Name: hc-passphrase
Version: 1.2.1
Summary: Generates cryptographically secure passphrases and passwords
Home-page: http://github.com/hackancuba/passphrase-py
Author: HacKan
Author-email: hackan@gmail.com
License: GNU GPL 3.0+
Download-URL: https://github.com/HacKanCuBa/passphrase-py/archive/v1.2.1.tar.gz
Keywords: cryptography passphrase password security
Platform: POSIX :: Linux
Classifier: Development Status :: 5 - Production/Stable
Classifier: Environment :: Console
Classifier: Intended Audience :: Developers
Classifier: Intended Audience :: End Users/Desktop
Classifier: License :: OSI Approved :: GNU General Public License v3 or later (GPLv3+)
Classifier: Natural Language :: English
Classifier: Operating System :: POSIX :: Linux
Classifier: Programming Language :: Python :: 3
Classifier: Programming Language :: Python :: 3.5
Classifier: Programming Language :: Python :: 3.6
Classifier: Topic :: Security :: Cryptography
Classifier: Topic :: Utilities
Requires-Python: >=3.5
